README.md
setup.cfg
setup.py
onp.egg-info/PKG-INFO
onp.egg-info/SOURCES.txt
onp.egg-info/dependency_links.txt
onp.egg-info/entry_points.txt
onp.egg-info/not-zip-safe
onp.egg-info/requires.txt
onp.egg-info/top_level.txt
src/__init__.py
src/version.py
src/video.py